ts_app/__init__.py
ts_app/__main__.py
ts_app/cli.py
ts_app/dash_app.py
ts_app/file_upload.py
ts_app/plotting.py
ts_app/ts_functions.py
ts_app/assets/background_large.jpg
ts_app/assets/background_small.jpg
ts_app/assets/dashboard_style.css
ts_app/assets/favicon.ico
ts_app/assets/glossary.json
ts_app/assets/ts.svg
ts_app/components/__init__.py
ts_app/components/modelling.py
ts_app/pages/__init__.py
ts_app/pages/glossary.py
ts_app/pages/home_page.py
ts_app/pages/sample.py
ts_app/pages/upload.py
ts_app-0.9.2.dist-info/LICENSE
ts_app-0.9.2.dist-info/METADATA
ts_app-0.9.2.dist-info/WHEEL
ts_app-0.9.2.dist-info/entry_points.txt
ts_app-0.9.2.dist-info/top_level.txt
ts_app-0.9.2.dist-info/RECORD
