Metadata-Version: 2.1
Name: ts_app
Version: 0.9.2
Summary: A simple dashboard application for interactively fitting ARIMA models.
Home-page: https://github.com/Tim-Abwao/time-series-app
Author: Abwao
Author-email: abwaomusungu@gmail.com
License: MIT
Keywords: time_series dashboard ARIMA
Classifier: Development Status :: 4 - Beta
Classifier: Programming Language :: Python :: 3.12
Requires-Python: >=3.10
License-File: LICENSE
Requires-Dist: dash>=2.18.2
Requires-Dist: openpyxl>=3.1.5
Requires-Dist: statsmodels>=0.14.4
Requires-Dist: waitress>=3.0.2
